MorEpiSim/IRD.py
MorEpiSim/graph.py
MorEpiSim/scores.py
MorEpiSim/the_env.py
MorEpiSim/the_env_old.py
MorEpiSim/the_env_test.py
MorEpiSim-0.0.2.dist-info/METADATA
MorEpiSim-0.0.2.dist-info/WHEEL
MorEpiSim-0.0.2.dist-info/top_level.txt
MorEpiSim-0.0.2.dist-info/RECORD
